kahi_minciencias_opendata_person/Kahi_minciencias_opendata_person.py
kahi_minciencias_opendata_person/__init__.py
kahi_minciencias_opendata_person/_version.py
Kahi_minciencias_opendata_person-0.1.4b0.dist-info/LICENSE
Kahi_minciencias_opendata_person-0.1.4b0.dist-info/METADATA
Kahi_minciencias_opendata_person-0.1.4b0.dist-info/WHEEL
Kahi_minciencias_opendata_person-0.1.4b0.dist-info/top_level.txt
Kahi_minciencias_opendata_person-0.1.4b0.dist-info/RECORD
