Metadata-Version: 2.2
Name: Kahi_minciencias_opendata_person
Version: 0.1.4b0
Summary: Kahi plugin minciencias_opendata_person
Home-page: https://github.com/colav/Kahi_plugins
Author: Colav
Author-email: colav@udea.edu.co
License: BSD
License-File: LICENSE
Requires-Dist: kahi
Requires-Dist: pymongo
Requires-Dist: pandas
Requires-Dist: thefuzz
Requires-Dist: datetime
Dynamic: author
Dynamic: author-email
Dynamic: description
Dynamic: description-content-type
Dynamic: home-page
Dynamic: license
Dynamic: requires-dist
Dynamic: summary
